<?xml version="1.0" encoding="UTF-8"?>
<GalleryItem ObjectType="1151" CSAOName="GalleryItem" Version="1.10"><Id>{15DE938A-7165-40BC-AE18-291FB2A26498}</Id><Name>AIRLINE</Name><Ordinal>0</Ordinal><GlobalOrder>0</GlobalOrder><Author>vfrolik</Author><CreatedDate>30.5.2011 12:58:33</CreatedDate><ModifiedDate>30.5.2011 12:58:33</ModifiedDate><Version>1.0</Version><Description></Description><SerializedModel>&lt;?xml version="1.0"?&gt;
&lt;LERModel ObjectType="4003" CSAOName="LERModel" InternalVersion="8.5" ProductVersion="4.0.6.7"&gt;&lt;Id&gt;{9B916059-DA49-47EE-A758-306707A6F5C0}&lt;/Id&gt;&lt;Name&gt;Logical model&lt;/Name&gt;&lt;Ordinal&gt;0&lt;/Ordinal&gt;&lt;GlobalOrder&gt;0&lt;/GlobalOrder&gt;&lt;ModelDefID&gt;{CA753C22-0089-4892-8EEE-8B3A09EA8AD3}&lt;/ModelDefID&gt;&lt;NamingConvFile&gt;&lt;/NamingConvFile&gt;&lt;NameMode&gt;0&lt;/NameMode&gt;&lt;WorkSpaces&gt;&lt;LERWorkSpace ObjectType="4501" CSAOName="LERWorkSpace"&gt;&lt;Id&gt;{CC2F334E-47E9-4DF0-9C7D-573B5021CAAB}&lt;/Id&gt;&lt;Name&gt;All Items&lt;/Name&gt;&lt;Ordinal&gt;0&lt;/Ordinal&gt;&lt;GlobalOrder&gt;0&lt;/GlobalOrder&gt;&lt;GalleryItemID&gt;{00000000-0000-0000-0000-000000000000}&lt;/GalleryItemID&gt;&lt;GalleryID&gt;{00000000-0000-0000-0000-000000000000}&lt;/GalleryID&gt;&lt;GalleryObjectID&gt;{00000000-0000-0000-0000-000000000000}&lt;/GalleryObjectID&gt;&lt;PenWidth&gt;1&lt;/PenWidth&gt;&lt;PenColor&gt;0&lt;/PenColor&gt;&lt;BrushColor&gt;15780518&lt;/BrushColor&gt;&lt;FontCharset&gt;238&lt;/FontCharset&gt;&lt;FontColor&gt;-16777208&lt;/FontColor&gt;&lt;FontName&gt;Arial&lt;/FontName&gt;&lt;FontStyle&gt;0&lt;/FontStyle&gt;&lt;BackgroundColor&gt;12639424&lt;/BackgroundColor&gt;&lt;RecalculateSize&gt;1&lt;/RecalculateSize&gt;&lt;FullBackground&gt;0&lt;/FullBackground&gt;&lt;Shadow&gt;1&lt;/Shadow&gt;&lt;DisplayLineNames&gt;1&lt;/DisplayLineNames&gt;&lt;FontHeight&gt;-28&lt;/FontHeight&gt;&lt;RightAngledLines&gt;0&lt;/RightAngledLines&gt;&lt;Grid&gt;0&lt;/Grid&gt;&lt;GridVisible&gt;0&lt;/GridVisible&gt;&lt;GridSize&gt;0&lt;/GridSize&gt;&lt;Description&gt;&lt;/Description&gt;&lt;EndType1&gt;0&lt;/EndType1&gt;&lt;EndType2&gt;0&lt;/EndType2&gt;&lt;ShapeList&gt;&lt;LERWorkSpaceShapeEntity ObjectType="4502" CSAOName="LERWorkSpaceShapeEntity"&gt;&lt;Id&gt;{1A704A3E-BF01-4C46-B180-56F160BE26FD}&lt;/Id&gt;&lt;Name&gt;FLIGHT&lt;/Name&gt;&lt;Ordinal&gt;0&lt;/Ordinal&gt;&lt;GlobalOrder&gt;0&lt;/GlobalOrder&gt;&lt;GalleryItemID&gt;{00000000-0000-0000-0000-000000000000}&lt;/GalleryItemID&gt;&lt;GalleryID&gt;{00000000-0000-0000-0000-000000000000}&lt;/GalleryID&gt;&lt;GalleryObjectID&gt;{00000000-0000-0000-0000-000000000000}&lt;/GalleryObjectID&gt;&lt;ParentBaseID&gt;{9A2B1CD2-2B6F-466F-82B2-E644B42C0F9D}&lt;/ParentBaseID&gt;&lt;PenWidth&gt;1&lt;/PenWidth&gt;&lt;PenColor&gt;0&lt;/PenColor&gt;&lt;BrushColor&gt;15780518&lt;/BrushColor&gt;&lt;FontCharset&gt;238&lt;/FontCharset&gt;&lt;FontColor&gt;-16777208&lt;/FontColor&gt;&lt;FontName&gt;Arial&lt;/FontName&gt;&lt;FontStyle&gt;0&lt;/FontStyle&gt;&lt;FormatLocked&gt;0&lt;/FormatLocked&gt;&lt;FontHeight&gt;-28&lt;/FontHeight&gt;&lt;ZOrder&gt;0&lt;/ZOrder&gt;&lt;Top&gt;725&lt;/Top&gt;&lt;Left&gt;900&lt;/Left&gt;&lt;z&gt;0&lt;/z&gt;&lt;Width&gt;140&lt;/Width&gt;&lt;Height&gt;190&lt;/Height&gt;&lt;dz&gt;0&lt;/dz&gt;&lt;RecalculateSizes&gt;1&lt;/RecalculateSizes&gt;&lt;UseWorkSpaceRecalculateSizes&gt;1&lt;/UseWorkSpaceRecalculateSizes&gt;&lt;Shadow&gt;1&lt;/Shadow&gt;&lt;FullBackground&gt;0&lt;/FullBackground&gt;&lt;LineList&gt;&lt;Id&gt;{6AFEF0BA-21FF-4349-B973-89AFF35E35B0}&lt;/Id&gt;&lt;Id&gt;{458C3183-90BE-492A-9ABB-5FCEFB8E0BD7}&lt;/Id&gt;&lt;Id&gt;{8624E532-F1B5-4B96-8315-663734E91847}&lt;/Id&gt;&lt;/LineList&gt;&lt;DisplayDataType&gt;0&lt;/DisplayDataType&gt;&lt;DisplayMode&gt;4&lt;/DisplayMode&gt;&lt;GraphicalKey&gt;1&lt;/GraphicalKey&gt;&lt;Align&gt;1&lt;/Align&gt;&lt;DisplayDomainName&gt;0&lt;/DisplayDomainName&gt;&lt;Gradient&gt;1&lt;/Gradient&gt;&lt;/LERWorkSpaceShapeEntity&gt;&lt;LERWorkSpaceShapeEntity ObjectType="4502" CSAOName="LERWorkSpaceShapeEntity"&gt;&lt;Id&gt;{533FC8B9-C6EB-4643-80F2-F455C6A04B6C}&lt;/Id&gt;&lt;Name&gt;SEGMENT&lt;/Name&gt;&lt;Ordinal&gt;0&lt;/Ordinal&gt;&lt;GlobalOrder&gt;0&lt;/GlobalOrder&gt;&lt;GalleryItemID&gt;{00000000-0000-0000-0000-000000000000}&lt;/GalleryItemID&gt;&lt;GalleryID&gt;{00000000-0000-0000-0000-000000000000}&lt;/GalleryID&gt;&lt;GalleryObjectID&gt;{00000000-0000-0000-0000-000000000000}&lt;/GalleryObjectID&gt;&lt;ParentBaseID&gt;{A65A5E4D-8AAE-47F6-A985-04CC5A7D9E38}&lt;/ParentBaseID&gt;&lt;PenWidth&gt;1&lt;/PenWidth&gt;&lt;PenColor&gt;0&lt;/PenColor&gt;&lt;BrushColor&gt;15780518&lt;/BrushColor&gt;&lt;FontCharset&gt;238&lt;/FontCharset&gt;&lt;FontColor&gt;-16777208&lt;/FontColor&gt;&lt;FontName&gt;Arial&lt;/FontName&gt;&lt;FontStyle&gt;0&lt;/FontStyle&gt;&lt;FormatLocked&gt;0&lt;/FormatLocked&gt;&lt;FontHeight&gt;-28&lt;/FontHeight&gt;&lt;ZOrder&gt;0&lt;/ZOrder&gt;&lt;Top&gt;725&lt;/Top&gt;&lt;Left&gt;1500&lt;/Left&gt;&lt;z&gt;0&lt;/z&gt;&lt;Width&gt;155&lt;/Width&gt;&lt;Height&gt;190&lt;/Height&gt;&lt;dz&gt;0&lt;/dz&gt;&lt;RecalculateSizes&gt;1&lt;/RecalculateSizes&gt;&lt;UseWorkSpaceRecalculateSizes&gt;1&lt;/UseWorkSpaceRecalculateSizes&gt;&lt;Shadow&gt;1&lt;/Shadow&gt;&lt;FullBackground&gt;0&lt;/FullBackground&gt;&lt;LineList&gt;&lt;Id&gt;{6AFEF0BA-21FF-4349-B973-89AFF35E35B0}&lt;/Id&gt;&lt;Id&gt;{5778A5D4-3559-4079-BD4A-E131F7979A5E}&lt;/Id&gt;&lt;Id&gt;{B859F61F-6358-4BF3-AF2D-DA32F06D3D95}&lt;/Id&gt;&lt;/LineList&gt;&lt;DisplayDataType&gt;0&lt;/DisplayDataType&gt;&lt;DisplayMode&gt;4&lt;/DisplayMode&gt;&lt;GraphicalKey&gt;1&lt;/GraphicalKey&gt;&lt;Align&gt;1&lt;/Align&gt;&lt;DisplayDomainName&gt;0&lt;/DisplayDomainName&gt;&lt;Gradient&gt;1&lt;/Gradient&gt;&lt;/LERWorkSpaceShapeEntity&gt;&lt;LERWorkSpaceShapeEntity ObjectType="4502" CSAOName="LERWorkSpaceShapeEntity"&gt;&lt;Id&gt;{5037E2CC-1760-41FC-AD29-F7F5C5A7D4AF}&lt;/Id&gt;&lt;Name&gt;AIRPORT&lt;/Name&gt;&lt;Ordinal&gt;0&lt;/Ordinal&gt;&lt;GlobalOrder&gt;0&lt;/GlobalOrder&gt;&lt;GalleryItemID&gt;{00000000-0000-0000-0000-000000000000}&lt;/GalleryItemID&gt;&lt;GalleryID&gt;{00000000-0000-0000-0000-000000000000}&lt;/GalleryID&gt;&lt;GalleryObjectID&gt;{00000000-0000-0000-0000-000000000000}&lt;/GalleryObjectID&gt;&lt;ParentBaseID&gt;{A8B650B9-F8E6-49F2-91D3-6ACFEB20D253}&lt;/ParentBaseID&gt;&lt;PenWidth&gt;1&lt;/PenWidth&gt;&lt;PenColor&gt;0&lt;/PenColor&gt;&lt;BrushColor&gt;15780518&lt;/BrushColor&gt;&lt;FontCharset&gt;238&lt;/FontCharset&gt;&lt;FontColor&gt;-16777208&lt;/FontColor&gt;&lt;FontName&gt;Arial&lt;/FontName&gt;&lt;FontStyle&gt;0&lt;/FontStyle&gt;&lt;FormatLocked&gt;0&lt;/FormatLocked&gt;&lt;FontHeight&gt;-28&lt;/FontHeight&gt;&lt;ZOrder&gt;0&lt;/ZOrder&gt;&lt;Top&gt;725&lt;/Top&gt;&lt;Left&gt;2071&lt;/Left&gt;&lt;z&gt;0&lt;/z&gt;&lt;Width&gt;142&lt;/Width&gt;&lt;Height&gt;190&lt;/Height&gt;&lt;dz&gt;0&lt;/dz&gt;&lt;RecalculateSizes&gt;1&lt;/RecalculateSizes&gt;&lt;UseWorkSpaceRecalculateSizes&gt;1&lt;/UseWorkSpaceRecalculateSizes&gt;&lt;Shadow&gt;1&lt;/Shadow&gt;&lt;FullBackground&gt;0&lt;/FullBackground&gt;&lt;LineList&gt;&lt;Id&gt;{5778A5D4-3559-4079-BD4A-E131F7979A5E}&lt;/Id&gt;&lt;Id&gt;{B859F61F-6358-4BF3-AF2D-DA32F06D3D95}&lt;/Id&gt;&lt;Id&gt;{46889D0E-88F1-49FA-882F-92DD10A676DB}&lt;/Id&gt;&lt;/LineList&gt;&lt;DisplayDataType&gt;0&lt;/DisplayDataType&gt;&lt;DisplayMode&gt;4&lt;/DisplayMode&gt;&lt;GraphicalKey&gt;1&lt;/GraphicalKey&gt;&lt;Align&gt;1&lt;/Align&gt;&lt;DisplayDomainName&gt;0&lt;/DisplayDomainName&gt;&lt;Gradient&gt;1&lt;/Gradient&gt;&lt;/LERWorkSpaceShapeEntity&gt;&lt;LERWorkSpaceShapeEntity ObjectType="4502" CSAOName="LERWorkSpaceShapeEntity"&gt;&lt;Id&gt;{4DA3B5EB-37F2-4810-A5EC-A0086A4CB268}&lt;/Id&gt;&lt;Name&gt;AIRLINE HUB&lt;/Name&gt;&lt;Ordinal&gt;0&lt;/Ordinal&gt;&lt;GlobalOrder&gt;0&lt;/GlobalOrder&gt;&lt;GalleryItemID&gt;{00000000-0000-0000-0000-000000000000}&lt;/GalleryItemID&gt;&lt;GalleryID&gt;{00000000-0000-0000-0000-000000000000}&lt;/GalleryID&gt;&lt;GalleryObjectID&gt;{00000000-0000-0000-0000-000000000000}&lt;/GalleryObjectID&gt;&lt;ParentBaseID&gt;{9FEDE1B8-AE03-4034-9750-699CB6B22C8F}&lt;/ParentBaseID&gt;&lt;PenWidth&gt;1&lt;/PenWidth&gt;&lt;PenColor&gt;0&lt;/PenColor&gt;&lt;BrushColor&gt;15780518&lt;/BrushColor&gt;&lt;FontCharset&gt;238&lt;/FontCharset&gt;&lt;FontColor&gt;-16777208&lt;/FontColor&gt;&lt;FontName&gt;Arial&lt;/FontName&gt;&lt;FontStyle&gt;0&lt;/FontStyle&gt;&lt;FormatLocked&gt;0&lt;/FormatLocked&gt;&lt;FontHeight&gt;-28&lt;/FontHeight&gt;&lt;ZOrder&gt;0&lt;/ZOrder&gt;&lt;Top&gt;125&lt;/Top&gt;&lt;Left&gt;2043&lt;/Left&gt;&lt;z&gt;0&lt;/z&gt;&lt;Width&gt;199&lt;/Width&gt;&lt;Height&gt;190&lt;/Height&gt;&lt;dz&gt;0&lt;/dz&gt;&lt;RecalculateSizes&gt;1&lt;/RecalculateSizes&gt;&lt;UseWorkSpaceRecalculateSizes&gt;1&lt;/UseWorkSpaceRecalculateSizes&gt;&lt;Shadow&gt;1&lt;/Shadow&gt;&lt;FullBackground&gt;0&lt;/FullBackground&gt;&lt;LineList&gt;&lt;Id&gt;{C3D0F419-EBCC-4D06-9458-C06B572601FC}&lt;/Id&gt;&lt;Id&gt;{46889D0E-88F1-49FA-882F-92DD10A676DB}&lt;/Id&gt;&lt;/LineList&gt;&lt;DisplayDataType&gt;0&lt;/DisplayDataType&gt;&lt;DisplayMode&gt;4&lt;/DisplayMode&gt;&lt;GraphicalKey&gt;1&lt;/GraphicalKey&gt;&lt;Align&gt;1&lt;/Align&gt;&lt;DisplayDomainName&gt;0&lt;/DisplayDomainName&gt;&lt;Gradient&gt;1&lt;/Gradient&gt;&lt;/LERWorkSpaceShapeEntity&gt;&lt;LERWorkSpaceShapeEntity ObjectType="4502" CSAOName="LERWorkSpaceShapeEntity"&gt;&lt;Id&gt;{3F5DD6FC-A9AA-4C39-985A-EAEAB3E7ECDB}&lt;/Id&gt;&lt;Name&gt;AIRLINE&lt;/Name&gt;&lt;Ordinal&gt;0&lt;/Ordinal&gt;&lt;GlobalOrder&gt;0&lt;/GlobalOrder&gt;&lt;GalleryItemID&gt;{00000000-0000-0000-0000-000000000000}&lt;/GalleryItemID&gt;&lt;GalleryID&gt;{00000000-0000-0000-0000-000000000000}&lt;/GalleryID&gt;&lt;GalleryObjectID&gt;{00000000-0000-0000-0000-000000000000}&lt;/GalleryObjectID&gt;&lt;ParentBaseID&gt;{73FF3EAB-FA33-4E71-98EE-7CEAECAF0835}&lt;/ParentBaseID&gt;&lt;PenWidth&gt;1&lt;/PenWidth&gt;&lt;PenColor&gt;0&lt;/PenColor&gt;&lt;BrushColor&gt;15780518&lt;/BrushColor&gt;&lt;FontCharset&gt;238&lt;/FontCharset&gt;&lt;FontColor&gt;-16777208&lt;/FontColor&gt;&lt;FontName&gt;Arial&lt;/FontName&gt;&lt;FontStyle&gt;0&lt;/FontStyle&gt;&lt;FormatLocked&gt;0&lt;/FormatLocked&gt;&lt;FontHeight&gt;-28&lt;/FontHeight&gt;&lt;ZOrder&gt;0&lt;/ZOrder&gt;&lt;Top&gt;125&lt;/Top&gt;&lt;Left&gt;900&lt;/Left&gt;&lt;z&gt;0&lt;/z&gt;&lt;Width&gt;140&lt;/Width&gt;&lt;Height&gt;190&lt;/Height&gt;&lt;dz&gt;0&lt;/dz&gt;&lt;RecalculateSizes&gt;1&lt;/RecalculateSizes&gt;&lt;UseWorkSpaceRecalculateSizes&gt;1&lt;/UseWorkSpaceRecalculateSizes&gt;&lt;Shadow&gt;1&lt;/Shadow&gt;&lt;FullBackground&gt;0&lt;/FullBackground&gt;&lt;LineList&gt;&lt;Id&gt;{458C3183-90BE-492A-9ABB-5FCEFB8E0BD7}&lt;/Id&gt;&lt;Id&gt;{C3D0F419-EBCC-4D06-9458-C06B572601FC}&lt;/Id&gt;&lt;/LineList&gt;&lt;DisplayDataType&gt;0&lt;/DisplayDataType&gt;&lt;DisplayMode&gt;4&lt;/DisplayMode&gt;&lt;GraphicalKey&gt;1&lt;/GraphicalKey&gt;&lt;Align&gt;1&lt;/Align&gt;&lt;DisplayDomainName&gt;0&lt;/DisplayDomainName&gt;&lt;Gradient&gt;1&lt;/Gradient&gt;&lt;/LERWorkSpaceShapeEntity&gt;&lt;LERWorkSpaceShapeEntity ObjectType="4502" CSAOName="LERWorkSpaceShapeEntity"&gt;&lt;Id&gt;{C6606D33-8FF0-417C-91C3-21BA587867D4}&lt;/Id&gt;&lt;Name&gt;BOOKING&lt;/Name&gt;&lt;Ordinal&gt;0&lt;/Ordinal&gt;&lt;GlobalOrder&gt;0&lt;/GlobalOrder&gt;&lt;GalleryItemID&gt;{00000000-0000-0000-0000-000000000000}&lt;/GalleryItemID&gt;&lt;GalleryID&gt;{00000000-0000-0000-0000-000000000000}&lt;/GalleryID&gt;&lt;GalleryObjectID&gt;{00000000-0000-0000-0000-000000000000}&lt;/GalleryObjectID&gt;&lt;ParentBaseID&gt;{E73C556E-8EAD-45C3-8C6C-455EFE009896}&lt;/ParentBaseID&gt;&lt;PenWidth&gt;1&lt;/PenWidth&gt;&lt;PenColor&gt;0&lt;/PenColor&gt;&lt;BrushColor&gt;15780518&lt;/BrushColor&gt;&lt;FontCharset&gt;238&lt;/FontCharset&gt;&lt;FontColor&gt;-16777208&lt;/FontColor&gt;&lt;FontName&gt;Arial&lt;/FontName&gt;&lt;FontStyle&gt;0&lt;/FontStyle&gt;&lt;FormatLocked&gt;0&lt;/FormatLocked&gt;&lt;FontHeight&gt;-28&lt;/FontHeight&gt;&lt;ZOrder&gt;0&lt;/ZOrder&gt;&lt;Top&gt;1252&lt;/Top&gt;&lt;Left&gt;895&lt;/Left&gt;&lt;z&gt;0&lt;/z&gt;&lt;Width&gt;151&lt;/Width&gt;&lt;Height&gt;190&lt;/Height&gt;&lt;dz&gt;0&lt;/dz&gt;&lt;RecalculateSizes&gt;1&lt;/RecalculateSizes&gt;&lt;UseWorkSpaceRecalculateSizes&gt;1&lt;/UseWorkSpaceRecalculateSizes&gt;&lt;Shadow&gt;1&lt;/Shadow&gt;&lt;FullBackground&gt;0&lt;/FullBackground&gt;&lt;LineList&gt;&lt;Id&gt;{8624E532-F1B5-4B96-8315-663734E91847}&lt;/Id&gt;&lt;Id&gt;{0023E762-2017-4B5B-955E-F3EE0E1CEF13}&lt;/Id&gt;&lt;/LineList&gt;&lt;DisplayDataType&gt;0&lt;/DisplayDataType&gt;&lt;DisplayMode&gt;4&lt;/DisplayMode&gt;&lt;GraphicalKey&gt;1&lt;/GraphicalKey&gt;&lt;Align&gt;1&lt;/Align&gt;&lt;DisplayDomainName&gt;0&lt;/DisplayDomainName&gt;&lt;Gradient&gt;1&lt;/Gradient&gt;&lt;/LERWorkSpaceShapeEntity&gt;&lt;LERWorkSpaceShapeEntity ObjectType="4502" CSAOName="LERWorkSpaceShapeEntity"&gt;&lt;Id&gt;{4F3E62FB-7507-4B5E-972F-27E756350073}&lt;/Id&gt;&lt;Name&gt;PASSENGER&lt;/Name&gt;&lt;Ordinal&gt;0&lt;/Ordinal&gt;&lt;GlobalOrder&gt;0&lt;/GlobalOrder&gt;&lt;GalleryItemID&gt;{00000000-0000-0000-0000-000000000000}&lt;/GalleryItemID&gt;&lt;GalleryID&gt;{00000000-0000-0000-0000-000000000000}&lt;/GalleryID&gt;&lt;GalleryObjectID&gt;{00000000-0000-0000-0000-000000000000}&lt;/GalleryObjectID&gt;&lt;ParentBaseID&gt;{B6B937F3-1340-4F80-8B87-B82EAA33FA08}&lt;/ParentBaseID&gt;&lt;PenWidth&gt;1&lt;/PenWidth&gt;&lt;PenColor&gt;0&lt;/PenColor&gt;&lt;BrushColor&gt;15780518&lt;/BrushColor&gt;&lt;FontCharset&gt;238&lt;/FontCharset&gt;&lt;FontColor&gt;-16777208&lt;/FontColor&gt;&lt;FontName&gt;Arial&lt;/FontName&gt;&lt;FontStyle&gt;0&lt;/FontStyle&gt;&lt;FormatLocked&gt;0&lt;/FormatLocked&gt;&lt;FontHeight&gt;-28&lt;/FontHeight&gt;&lt;ZOrder&gt;0&lt;/ZOrder&gt;&lt;Top&gt;1252&lt;/Top&gt;&lt;Left&gt;168&lt;/Left&gt;&lt;z&gt;0&lt;/z&gt;&lt;Width&gt;199&lt;/Width&gt;&lt;Height&gt;190&lt;/Height&gt;&lt;dz&gt;0&lt;/dz&gt;&lt;RecalculateSizes&gt;1&lt;/RecalculateSizes&gt;&lt;UseWorkSpaceRecalculateSizes&gt;1&lt;/UseWorkSpaceRecalculateSizes&gt;&lt;Shadow&gt;1&lt;/Shadow&gt;&lt;FullBackground&gt;0&lt;/FullBackground&gt;&lt;LineList&gt;&lt;Id&gt;{0023E762-2017-4B5B-955E-F3EE0E1CEF13}&lt;/Id&gt;&lt;/LineList&gt;&lt;DisplayDataType&gt;0&lt;/DisplayDataType&gt;&lt;DisplayMode&gt;4&lt;/DisplayMode&gt;&lt;GraphicalKey&gt;1&lt;/GraphicalKey&gt;&lt;Align&gt;1&lt;/Align&gt;&lt;DisplayDomainName&gt;0&lt;/DisplayDomainName&gt;&lt;Gradient&gt;1&lt;/Gradient&gt;&lt;/LERWorkSpaceShapeEntity&gt;&lt;/ShapeList&gt;&lt;LineList&gt;&lt;LERWorkSpaceLineRelation ObjectType="4503" CSAOName="LERWorkSpaceLineRelation"&gt;&lt;Id&gt;{6AFEF0BA-21FF-4349-B973-89AFF35E35B0}&lt;/Id&gt;&lt;Name&gt;IS COMPSED OF&lt;/Name&gt;&lt;Ordinal&gt;0&lt;/Ordinal&gt;&lt;GlobalOrder&gt;0&lt;/GlobalOrder&gt;&lt;GalleryItemID&gt;{00000000-0000-0000-0000-000000000000}&lt;/GalleryItemID&gt;&lt;GalleryID&gt;{00000000-0000-0000-0000-000000000000}&lt;/GalleryID&gt;&lt;GalleryObjectID&gt;{00000000-0000-0000-0000-000000000000}&lt;/GalleryObjectID&gt;&lt;ParentBaseID&gt;{8DAAF463-552E-4894-9ED0-4DC72D684782}&lt;/ParentBaseID&gt;&lt;PenWidth&gt;1&lt;/PenWidth&gt;&lt;PenColor&gt;0&lt;/PenColor&gt;&lt;BrushColor&gt;16777215&lt;/BrushColor&gt;&lt;FontCharset&gt;238&lt;/FontCharset&gt;&lt;FontColor&gt;-16777208&lt;/FontColor&gt;&lt;FontName&gt;Arial&lt;/FontName&gt;&lt;FontStyle&gt;0&lt;/FontStyle&gt;&lt;FormatLocked&gt;0&lt;/FormatLocked&gt;&lt;FontHeight&gt;-28&lt;/FontHeight&gt;&lt;ZOrder&gt;-10&lt;/ZOrder&gt;&lt;WorkSpaceShape1&gt;&lt;Id&gt;{1A704A3E-BF01-4C46-B180-56F160BE26FD}&lt;/Id&gt;&lt;/WorkSpaceShape1&gt;&lt;WorkSpaceShape2&gt;&lt;Id&gt;{533FC8B9-C6EB-4643-80F2-F455C6A04B6C}&lt;/Id&gt;&lt;/WorkSpaceShape2&gt;&lt;NamePositionY&gt;0&lt;/NamePositionY&gt;&lt;NamePositionX&gt;0&lt;/NamePositionX&gt;&lt;Points&gt;&lt;Point&gt;&lt;x&gt;1040&lt;/x&gt;&lt;y&gt;820&lt;/y&gt;&lt;/Point&gt;&lt;Point&gt;&lt;x&gt;1071&lt;/x&gt;&lt;y&gt;820&lt;/y&gt;&lt;/Point&gt;&lt;Point&gt;&lt;x&gt;1469&lt;/x&gt;&lt;y&gt;820&lt;/y&gt;&lt;/Point&gt;&lt;Point&gt;&lt;x&gt;1500&lt;/x&gt;&lt;y&gt;820&lt;/y&gt;&lt;/Point&gt;&lt;/Points&gt;&lt;/LERWorkSpaceLineRelation&gt;&lt;LERWorkSpaceLineRelation ObjectType="4503" CSAOName="LERWorkSpaceLineRelation"&gt;&lt;Id&gt;{5778A5D4-3559-4079-BD4A-E131F7979A5E}&lt;/Id&gt;&lt;Name&gt;STARTS AT&lt;/Name&gt;&lt;Ordinal&gt;0&lt;/Ordinal&gt;&lt;GlobalOrder&gt;0&lt;/GlobalOrder&gt;&lt;GalleryItemID&gt;{00000000-0000-0000-0000-000000000000}&lt;/GalleryItemID&gt;&lt;GalleryID&gt;{00000000-0000-0000-0000-000000000000}&lt;/GalleryID&gt;&lt;GalleryObjectID&gt;{00000000-0000-0000-0000-000000000000}&lt;/GalleryObjectID&gt;&lt;ParentBaseID&gt;{EDC7E0DE-DA0F-4360-854B-1422CF6AF10C}&lt;/ParentBaseID&gt;&lt;PenWidth&gt;1&lt;/PenWidth&gt;&lt;PenColor&gt;0&lt;/PenColor&gt;&lt;BrushColor&gt;16777215&lt;/BrushColor&gt;&lt;FontCharset&gt;238&lt;/FontCharset&gt;&lt;FontColor&gt;-16777208&lt;/FontColor&gt;&lt;FontName&gt;Arial&lt;/FontName&gt;&lt;FontStyle&gt;0&lt;/FontStyle&gt;&lt;FormatLocked&gt;0&lt;/FormatLocked&gt;&lt;FontHeight&gt;-28&lt;/FontHeight&gt;&lt;ZOrder&gt;-10&lt;/ZOrder&gt;&lt;WorkSpaceShape1&gt;&lt;Id&gt;{5037E2CC-1760-41FC-AD29-F7F5C5A7D4AF}&lt;/Id&gt;&lt;/WorkSpaceShape1&gt;&lt;WorkSpaceShape2&gt;&lt;Id&gt;{533FC8B9-C6EB-4643-80F2-F455C6A04B6C}&lt;/Id&gt;&lt;/WorkSpaceShape2&gt;&lt;NamePositionY&gt;0&lt;/NamePositionY&gt;&lt;NamePositionX&gt;0&lt;/NamePositionX&gt;&lt;Points&gt;&lt;Point&gt;&lt;x&gt;2071&lt;/x&gt;&lt;y&gt;788&lt;/y&gt;&lt;/Point&gt;&lt;Point&gt;&lt;x&gt;2040&lt;/x&gt;&lt;y&gt;788&lt;/y&gt;&lt;/Point&gt;&lt;Point&gt;&lt;x&gt;1686&lt;/x&gt;&lt;y&gt;788&lt;/y&gt;&lt;/Point&gt;&lt;Point&gt;&lt;x&gt;1655&lt;/x&gt;&lt;y&gt;788&lt;/y&gt;&lt;/Point&gt;&lt;/Points&gt;&lt;/LERWorkSpaceLineRelation&gt;&lt;LERWorkSpaceLineRelation ObjectType="4503" CSAOName="LERWorkSpaceLineRelation"&gt;&lt;Id&gt;{B859F61F-6358-4BF3-AF2D-DA32F06D3D95}&lt;/Id&gt;&lt;Name&gt;ENDS AT&lt;/Name&gt;&lt;Ordinal&gt;0&lt;/Ordinal&gt;&lt;GlobalOrder&gt;0&lt;/GlobalOrder&gt;&lt;GalleryItemID&gt;{00000000-0000-0000-0000-000000000000}&lt;/GalleryItemID&gt;&lt;GalleryID&gt;{00000000-0000-0000-0000-000000000000}&lt;/GalleryID&gt;&lt;GalleryObjectID&gt;{00000000-0000-0000-0000-000000000000}&lt;/GalleryObjectID&gt;&lt;ParentBaseID&gt;{20159913-BD6E-4899-AE26-05EC27540D3B}&lt;/ParentBaseID&gt;&lt;PenWidth&gt;1&lt;/PenWidth&gt;&lt;PenColor&gt;0&lt;/PenColor&gt;&lt;BrushColor&gt;16777215&lt;/BrushColor&gt;&lt;FontCharset&gt;238&lt;/FontCharset&gt;&lt;FontColor&gt;-16777208&lt;/FontColor&gt;&lt;FontName&gt;Arial&lt;/FontName&gt;&lt;FontStyle&gt;0&lt;/FontStyle&gt;&lt;FormatLocked&gt;0&lt;/FormatLocked&gt;&lt;FontHeight&gt;-28&lt;/FontHeight&gt;&lt;ZOrder&gt;-10&lt;/ZOrder&gt;&lt;WorkSpaceShape1&gt;&lt;Id&gt;{5037E2CC-1760-41FC-AD29-F7F5C5A7D4AF}&lt;/Id&gt;&lt;/WorkSpaceShape1&gt;&lt;WorkSpaceShape2&gt;&lt;Id&gt;{533FC8B9-C6EB-4643-80F2-F455C6A04B6C}&lt;/Id&gt;&lt;/WorkSpaceShape2&gt;&lt;NamePositionY&gt;0&lt;/NamePositionY&gt;&lt;NamePositionX&gt;0&lt;/NamePositionX&gt;&lt;Points&gt;&lt;Point&gt;&lt;x&gt;2071&lt;/x&gt;&lt;y&gt;852&lt;/y&gt;&lt;/Point&gt;&lt;Point&gt;&lt;x&gt;2040&lt;/x&gt;&lt;y&gt;852&lt;/y&gt;&lt;/Point&gt;&lt;Point&gt;&lt;x&gt;1686&lt;/x&gt;&lt;y&gt;852&lt;/y&gt;&lt;/Point&gt;&lt;Point&gt;&lt;x&gt;1655&lt;/x&gt;&lt;y&gt;852&lt;/y&gt;&lt;/Point&gt;&lt;/Points&gt;&lt;/LERWorkSpaceLineRelation&gt;&lt;LERWorkSpaceLineRelation ObjectType="4503" CSAOName="LERWorkSpaceLineRelation"&gt;&lt;Id&gt;{458C3183-90BE-492A-9ABB-5FCEFB8E0BD7}&lt;/Id&gt;&lt;Name&gt;OFFERS&lt;/Name&gt;&lt;Ordinal&gt;0&lt;/Ordinal&gt;&lt;GlobalOrder&gt;0&lt;/GlobalOrder&gt;&lt;GalleryItemID&gt;{00000000-0000-0000-0000-000000000000}&lt;/GalleryItemID&gt;&lt;GalleryID&gt;{00000000-0000-0000-0000-000000000000}&lt;/GalleryID&gt;&lt;GalleryObjectID&gt;{00000000-0000-0000-0000-000000000000}&lt;/GalleryObjectID&gt;&lt;ParentBaseID&gt;{2E8963DB-958B-4CA1-819F-A791E7FF4E0A}&lt;/ParentBaseID&gt;&lt;PenWidth&gt;1&lt;/PenWidth&gt;&lt;PenColor&gt;0&lt;/PenColor&gt;&lt;BrushColor&gt;16777215&lt;/BrushColor&gt;&lt;FontCharset&gt;238&lt;/FontCharset&gt;&lt;FontColor&gt;-16777208&lt;/FontColor&gt;&lt;FontName&gt;Arial&lt;/FontName&gt;&lt;FontStyle&gt;0&lt;/FontStyle&gt;&lt;FormatLocked&gt;0&lt;/FormatLocked&gt;&lt;FontHeight&gt;-28&lt;/FontHeight&gt;&lt;ZOrder&gt;-10&lt;/ZOrder&gt;&lt;WorkSpaceShape1&gt;&lt;Id&gt;{3F5DD6FC-A9AA-4C39-985A-EAEAB3E7ECDB}&lt;/Id&gt;&lt;/WorkSpaceShape1&gt;&lt;WorkSpaceShape2&gt;&lt;Id&gt;{1A704A3E-BF01-4C46-B180-56F160BE26FD}&lt;/Id&gt;&lt;/WorkSpaceShape2&gt;&lt;NamePositionY&gt;0&lt;/NamePositionY&gt;&lt;NamePositionX&gt;0&lt;/NamePositionX&gt;&lt;Points&gt;&lt;Point&gt;&lt;x&gt;970&lt;/x&gt;&lt;y&gt;315&lt;/y&gt;&lt;/Point&gt;&lt;Point&gt;&lt;x&gt;970&lt;/x&gt;&lt;y&gt;346&lt;/y&gt;&lt;/Point&gt;&lt;Point&gt;&lt;x&gt;970&lt;/x&gt;&lt;y&gt;694&lt;/y&gt;&lt;/Point&gt;&lt;Point&gt;&lt;x&gt;970&lt;/x&gt;&lt;y&gt;725&lt;/y&gt;&lt;/Point&gt;&lt;/Points&gt;&lt;/LERWorkSpaceLineRelation&gt;&lt;LERWorkSpaceLineRelation ObjectType="4503" CSAOName="LERWorkSpaceLineRelation"&gt;&lt;Id&gt;{C3D0F419-EBCC-4D06-9458-C06B572601FC}&lt;/Id&gt;&lt;Name&gt;AIRLINE - AIRLINE HUB&lt;/Name&gt;&lt;Ordinal&gt;0&lt;/Ordinal&gt;&lt;GlobalOrder&gt;0&lt;/GlobalOrder&gt;&lt;GalleryItemID&gt;{00000000-0000-0000-0000-000000000000}&lt;/GalleryItemID&gt;&lt;GalleryID&gt;{00000000-0000-0000-0000-000000000000}&lt;/GalleryID&gt;&lt;GalleryObjectID&gt;{00000000-0000-0000-0000-000000000000}&lt;/GalleryObjectID&gt;&lt;ParentBaseID&gt;{E1282207-BC87-4E97-A51E-17CBDD5D42CC}&lt;/ParentBaseID&gt;&lt;PenWidth&gt;1&lt;/PenWidth&gt;&lt;PenColor&gt;0&lt;/PenColor&gt;&lt;BrushColor&gt;16777215&lt;/BrushColor&gt;&lt;FontCharset&gt;238&lt;/FontCharset&gt;&lt;FontColor&gt;-16777208&lt;/FontColor&gt;&lt;FontName&gt;Arial&lt;/FontName&gt;&lt;FontStyle&gt;0&lt;/FontStyle&gt;&lt;FormatLocked&gt;0&lt;/FormatLocked&gt;&lt;FontHeight&gt;-28&lt;/FontHeight&gt;&lt;ZOrder&gt;-10&lt;/ZOrder&gt;&lt;WorkSpaceShape1&gt;&lt;Id&gt;{3F5DD6FC-A9AA-4C39-985A-EAEAB3E7ECDB}&lt;/Id&gt;&lt;/WorkSpaceShape1&gt;&lt;WorkSpaceShape2&gt;&lt;Id&gt;{4DA3B5EB-37F2-4810-A5EC-A0086A4CB268}&lt;/Id&gt;&lt;/WorkSpaceShape2&gt;&lt;NamePositionY&gt;0&lt;/NamePositionY&gt;&lt;NamePositionX&gt;0&lt;/NamePositionX&gt;&lt;Points&gt;&lt;Point&gt;&lt;x&gt;1040&lt;/x&gt;&lt;y&gt;220&lt;/y&gt;&lt;/Point&gt;&lt;Point&gt;&lt;x&gt;1071&lt;/x&gt;&lt;y&gt;220&lt;/y&gt;&lt;/Point&gt;&lt;Point&gt;&lt;x&gt;2012&lt;/x&gt;&lt;y&gt;220&lt;/y&gt;&lt;/Point&gt;&lt;Point&gt;&lt;x&gt;2043&lt;/x&gt;&lt;y&gt;220&lt;/y&gt;&lt;/Point&gt;&lt;/Points&gt;&lt;/LERWorkSpaceLineRelation&gt;&lt;LERWorkSpaceLineRelation ObjectType="4503" CSAOName="LERWorkSpaceLineRelation"&gt;&lt;Id&gt;{46889D0E-88F1-49FA-882F-92DD10A676DB}&lt;/Id&gt;&lt;Name&gt;AIRPORT - AIRLINE HUB&lt;/Name&gt;&lt;Ordinal&gt;0&lt;/Ordinal&gt;&lt;GlobalOrder&gt;0&lt;/GlobalOrder&gt;&lt;GalleryItemID&gt;{00000000-0000-0000-0000-000000000000}&lt;/GalleryItemID&gt;&lt;GalleryID&gt;{00000000-0000-0000-0000-000000000000}&lt;/GalleryID&gt;&lt;GalleryObjectID&gt;{00000000-0000-0000-0000-000000000000}&lt;/GalleryObjectID&gt;&lt;ParentBaseID&gt;{C134E1E3-1D12-4CA8-8313-03AB7E6D80DB}&lt;/ParentBaseID&gt;&lt;PenWidth&gt;1&lt;/PenWidth&gt;&lt;PenColor&gt;0&lt;/PenColor&gt;&lt;BrushColor&gt;16777215&lt;/BrushColor&gt;&lt;FontCharset&gt;238&lt;/FontCharset&gt;&lt;FontColor&gt;-16777208&lt;/FontColor&gt;&lt;FontName&gt;Arial&lt;/FontName&gt;&lt;FontStyle&gt;0&lt;/FontStyle&gt;&lt;FormatLocked&gt;0&lt;/FormatLocked&gt;&lt;FontHeight&gt;-28&lt;/FontHeight&gt;&lt;ZOrder&gt;-10&lt;/ZOrder&gt;&lt;WorkSpaceShape1&gt;&lt;Id&gt;{5037E2CC-1760-41FC-AD29-F7F5C5A7D4AF}&lt;/Id&gt;&lt;/WorkSpaceShape1&gt;&lt;WorkSpaceShape2&gt;&lt;Id&gt;{4DA3B5EB-37F2-4810-A5EC-A0086A4CB268}&lt;/Id&gt;&lt;/WorkSpaceShape2&gt;&lt;NamePositionY&gt;0&lt;/NamePositionY&gt;&lt;NamePositionX&gt;0&lt;/NamePositionX&gt;&lt;Points&gt;&lt;Point&gt;&lt;x&gt;2142&lt;/x&gt;&lt;y&gt;725&lt;/y&gt;&lt;/Point&gt;&lt;Point&gt;&lt;x&gt;2142&lt;/x&gt;&lt;y&gt;694&lt;/y&gt;&lt;/Point&gt;&lt;Point&gt;&lt;x&gt;2142&lt;/x&gt;&lt;y&gt;346&lt;/y&gt;&lt;/Point&gt;&lt;Point&gt;&lt;x&gt;2142&lt;/x&gt;&lt;y&gt;315&lt;/y&gt;&lt;/Point&gt;&lt;/Points&gt;&lt;/LERWorkSpaceLineRelation&gt;&lt;LERWorkSpaceLineRelation ObjectType="4503" CSAOName="LERWorkSpaceLineRelation"&gt;&lt;Id&gt;{8624E532-F1B5-4B96-8315-663734E91847}&lt;/Id&gt;&lt;Name&gt;FLIGHT - BOOKING&lt;/Name&gt;&lt;Ordinal&gt;0&lt;/Ordinal&gt;&lt;GlobalOrder&gt;0&lt;/GlobalOrder&gt;&lt;GalleryItemID&gt;{00000000-0000-0000-0000-000000000000}&lt;/GalleryItemID&gt;&lt;GalleryID&gt;{00000000-0000-0000-0000-000000000000}&lt;/GalleryID&gt;&lt;GalleryObjectID&gt;{00000000-0000-0000-0000-000000000000}&lt;/GalleryObjectID&gt;&lt;ParentBaseID&gt;{05A12837-4349-49CD-A54E-AD9D1A20CB4F}&lt;/ParentBaseID&gt;&lt;PenWidth&gt;1&lt;/PenWidth&gt;&lt;PenColor&gt;0&lt;/PenColor&gt;&lt;BrushColor&gt;16777215&lt;/BrushColor&gt;&lt;FontCharset&gt;238&lt;/FontCharset&gt;&lt;FontColor&gt;-16777208&lt;/FontColor&gt;&lt;FontName&gt;Arial&lt;/FontName&gt;&lt;FontStyle&gt;0&lt;/FontStyle&gt;&lt;FormatLocked&gt;0&lt;/FormatLocked&gt;&lt;FontHeight&gt;-28&lt;/FontHeight&gt;&lt;ZOrder&gt;-10&lt;/ZOrder&gt;&lt;WorkSpaceShape1&gt;&lt;Id&gt;{1A704A3E-BF01-4C46-B180-56F160BE26FD}&lt;/Id&gt;&lt;/WorkSpaceShape1&gt;&lt;WorkSpaceShape2&gt;&lt;Id&gt;{C6606D33-8FF0-417C-91C3-21BA587867D4}&lt;/Id&gt;&lt;/WorkSpaceShape2&gt;&lt;NamePositionY&gt;0&lt;/NamePositionY&gt;&lt;NamePositionX&gt;0&lt;/NamePositionX&gt;&lt;Points&gt;&lt;Point&gt;&lt;x&gt;970&lt;/x&gt;&lt;y&gt;915&lt;/y&gt;&lt;/Point&gt;&lt;Point&gt;&lt;x&gt;970&lt;/x&gt;&lt;y&gt;946&lt;/y&gt;&lt;/Point&gt;&lt;Point&gt;&lt;x&gt;970&lt;/x&gt;&lt;y&gt;1221&lt;/y&gt;&lt;/Point&gt;&lt;Point&gt;&lt;x&gt;970&lt;/x&gt;&lt;y&gt;1252&lt;/y&gt;&lt;/Point&gt;&lt;/Points&gt;&lt;/LERWorkSpaceLineRelation&gt;&lt;LERWorkSpaceLineRelation ObjectType="4503" CSAOName="LERWorkSpaceLineRelation"&gt;&lt;Id&gt;{0023E762-2017-4B5B-955E-F3EE0E1CEF13}&lt;/Id&gt;&lt;Name&gt;PASSENGER - BOOKING&lt;/Name&gt;&lt;Ordinal&gt;0&lt;/Ordinal&gt;&lt;GlobalOrder&gt;0&lt;/GlobalOrder&gt;&lt;GalleryItemID&gt;{00000000-0000-0000-0000-000000000000}&lt;/GalleryItemID&gt;&lt;GalleryID&gt;{00000000-0000-0000-0000-000000000000}&lt;/GalleryID&gt;&lt;GalleryObjectID&gt;{00000000-0000-0000-0000-000000000000}&lt;/GalleryObjectID&gt;&lt;ParentBaseID&gt;{086F513C-E661-4292-9E4F-8FA8C4C817BE}&lt;/ParentBaseID&gt;&lt;PenWidth&gt;1&lt;/PenWidth&gt;&lt;PenColor&gt;0&lt;/PenColor&gt;&lt;BrushColor&gt;16777215&lt;/BrushColor&gt;&lt;FontCharset&gt;238&lt;/FontCharset&gt;&lt;FontColor&gt;-16777208&lt;/FontColor&gt;&lt;FontName&gt;Arial&lt;/FontName&gt;&lt;FontStyle&gt;0&lt;/FontStyle&gt;&lt;FormatLocked&gt;0&lt;/FormatLocked&gt;&lt;FontHeight&gt;-28&lt;/FontHeight&gt;&lt;ZOrder&gt;-10&lt;/ZOrder&gt;&lt;WorkSpaceShape1&gt;&lt;Id&gt;{4F3E62FB-7507-4B5E-972F-27E756350073}&lt;/Id&gt;&lt;/WorkSpaceShape1&gt;&lt;WorkSpaceShape2&gt;&lt;Id&gt;{C6606D33-8FF0-417C-91C3-21BA587867D4}&lt;/Id&gt;&lt;/WorkSpaceShape2&gt;&lt;NamePositionY&gt;0&lt;/NamePositionY&gt;&lt;NamePositionX&gt;0&lt;/NamePositionX&gt;&lt;Points&gt;&lt;Point&gt;&lt;x&gt;367&lt;/x&gt;&lt;y&gt;1347&lt;/y&gt;&lt;/Point&gt;&lt;Point&gt;&lt;x&gt;398&lt;/x&gt;&lt;y&gt;1347&lt;/y&gt;&lt;/Point&gt;&lt;Point&gt;&lt;x&gt;864&lt;/x&gt;&lt;y&gt;1347&lt;/y&gt;&lt;/Point&gt;&lt;Point&gt;&lt;x&gt;895&lt;/x&gt;&lt;y&gt;1347&lt;/y&gt;&lt;/Point&gt;&lt;/Points&gt;&lt;/LERWorkSpaceLineRelation&gt;&lt;/LineList&gt;&lt;Page&gt;&lt;WorkSpacePage ObjectType="1511" CSAOName="WorkSpacePage"&gt;&lt;Id&gt;{80F6EE3D-F0BD-4BEA-AEE3-43EA614B6B6F}&lt;/Id&gt;&lt;Name&gt;Page Format&lt;/Name&gt;&lt;Ordinal&gt;0&lt;/Ordinal&gt;&lt;GlobalOrder&gt;0&lt;/GlobalOrder&gt;&lt;Zoom&gt;100&lt;/Zoom&gt;&lt;FitToPage&gt;0&lt;/FitToPage&gt;&lt;Orientation&gt;0&lt;/Orientation&gt;&lt;HeightDec&gt;2970&lt;/HeightDec&gt;&lt;WidthDec&gt;2100&lt;/WidthDec&gt;&lt;MarginBottomDec&gt;150&lt;/MarginBottomDec&gt;&lt;MarginLeftDec&gt;100&lt;/MarginLeftDec&gt;&lt;MarginRightDec&gt;100&lt;/MarginRightDec&gt;&lt;MarginTopDec&gt;150&lt;/MarginTopDec&gt;&lt;/WorkSpacePage&gt;&lt;/Page&gt;&lt;Align&gt;1&lt;/Align&gt;&lt;DisplayDataType&gt;0&lt;/DisplayDataType&gt;&lt;GraphicalKey&gt;1&lt;/GraphicalKey&gt;&lt;DisplayMode&gt;4&lt;/DisplayMode&gt;&lt;DisplayDomainName&gt;0&lt;/DisplayDomainName&gt;&lt;AutoFill&gt;1&lt;/AutoFill&gt;&lt;Notation&gt;0&lt;/Notation&gt;&lt;Gradient&gt;1&lt;/Gradient&gt;&lt;/LERWorkSpace&gt;&lt;/WorkSpaces&gt;&lt;Categories/&gt;&lt;ToDoItems/&gt;&lt;Notes/&gt;&lt;NoteLines/&gt;&lt;ModelTitle&gt;&lt;ModelTitle ObjectType="1011" CSAOName="ModelTitle"&gt;&lt;Id&gt;{7EEA66DB-FA4E-42F5-B7FC-B77CAC468CAF}&lt;/Id&gt;&lt;Ordinal&gt;0&lt;/Ordinal&gt;&lt;GlobalOrder&gt;0&lt;/GlobalOrder&gt;&lt;GalleryItemID&gt;{00000000-0000-0000-0000-000000000000}&lt;/GalleryItemID&gt;&lt;GalleryID&gt;{00000000-0000-0000-0000-000000000000}&lt;/GalleryID&gt;&lt;GalleryObjectID&gt;{00000000-0000-0000-0000-000000000000}&lt;/GalleryObjectID&gt;&lt;ModelName&gt;Logical model&lt;/ModelName&gt;&lt;Author&gt;&lt;/Author&gt;&lt;Company&gt;&lt;/Company&gt;&lt;Version&gt;&lt;/Version&gt;&lt;CreatedDate&gt;2011-05-30T12:58:22.828+02:00&lt;/CreatedDate&gt;&lt;ModifiedDate&gt;2011-05-30T12:58:22.828+02:00&lt;/ModifiedDate&gt;&lt;Project&gt;&lt;/Project&gt;&lt;Description&gt;&lt;/Description&gt;&lt;/ModelTitle&gt;&lt;/ModelTitle&gt;&lt;Verificators&gt;&lt;LERVerificator ObjectType="4017" CSAOName="LERVerificator"&gt;&lt;Id&gt;{B95A00C0-D106-472B-90D8-4A8AFE8F7E80}&lt;/Id&gt;&lt;Name&gt;&lt;/Name&gt;&lt;Ordinal&gt;0&lt;/Ordinal&gt;&lt;GlobalOrder&gt;0&lt;/GlobalOrder&gt;&lt;ShowHints&gt;0&lt;/ShowHints&gt;&lt;ShowWarnings&gt;1&lt;/ShowWarnings&gt;&lt;CheckIfEntityIsEmpty&gt;1&lt;/CheckIfEntityIsEmpty&gt;&lt;CheckEntityNameDuplicity&gt;1&lt;/CheckEntityNameDuplicity&gt;&lt;CheckRelationNameDuplicity&gt;1&lt;/CheckRelationNameDuplicity&gt;&lt;CheckInheritanceNameDuplicity&gt;1&lt;/CheckInheritanceNameDuplicity&gt;&lt;CheckRuleNameDuplicity&gt;1&lt;/CheckRuleNameDuplicity&gt;&lt;CheckDomainNameDuplicity&gt;1&lt;/CheckDomainNameDuplicity&gt;&lt;CheckDefaultNameDuplicity&gt;1&lt;/CheckDefaultNameDuplicity&gt;&lt;CheckKeyNameDuplicity&gt;1&lt;/CheckKeyNameDuplicity&gt;&lt;/LERVerificator&gt;&lt;/Verificators&gt;&lt;DefaultVerificator&gt;&lt;Id&gt;{B95A00C0-D106-472B-90D8-4A8AFE8F7E80}&lt;/Id&gt;&lt;/DefaultVerificator&gt;&lt;DefaultCodeGenerator&gt;&lt;Id&gt;{145C3E38-EF82-435B-9A84-4D9C29DCBD90}&lt;/Id&gt;&lt;/DefaultCodeGenerator&gt;&lt;CodeGenerators&gt;&lt;CodeGenerator ObjectType="1044" CSAOName="CodeGenerator"&gt;&lt;Id&gt;{145C3E38-EF82-435B-9A84-4D9C29DCBD90}&lt;/Id&gt;&lt;GlobalOrder&gt;0&lt;/GlobalOrder&gt;&lt;FileName&gt;&lt;/FileName&gt;&lt;GenerateFromModel&gt;0&lt;/GenerateFromModel&gt;&lt;GenerateWorkspaceID&gt;{00000000-0000-0000-0000-000000000000}&lt;/GenerateWorkspaceID&gt;&lt;PreviewBeforeSave&gt;0&lt;/PreviewBeforeSave&gt;&lt;TextCaseIndex&gt;0&lt;/TextCaseIndex&gt;&lt;SelectedObjects/&gt;&lt;OrderSettings/&gt;&lt;/CodeGenerator&gt;&lt;/CodeGenerators&gt;&lt;ReportConfigs/&gt;&lt;DefaultDataSources&gt;&lt;DefaultDataSourceConvertor ObjectType="1068" CSAOName="DefaultDataSourceConvertor"&gt;&lt;Id&gt;{EAE42ED5-9E19-463D-A192-019876A430BE}&lt;/Id&gt;&lt;Name&gt;&lt;/Name&gt;&lt;Ordinal&gt;0&lt;/Ordinal&gt;&lt;GlobalOrder&gt;0&lt;/GlobalOrder&gt;&lt;Model1FileName&gt;&lt;/Model1FileName&gt;&lt;Model2FileName&gt;&lt;/Model2FileName&gt;&lt;Converted&gt;0&lt;/Converted&gt;&lt;/DefaultDataSourceConvertor&gt;&lt;/DefaultDataSources&gt;&lt;Images/&gt;&lt;Rectangles/&gt;&lt;Ellipses/&gt;&lt;SimpleTexts/&gt;&lt;LabelEllipses/&gt;&lt;LabelQuadrangles/&gt;&lt;Entities&gt;&lt;LEREntity ObjectType="4004" CSAOName="LEREntity"&gt;&lt;Id&gt;{9A2B1CD2-2B6F-466F-82B2-E644B42C0F9D}&lt;/Id&gt;&lt;Name&gt;FLIGHT&lt;/Name&gt;&lt;Ordinal&gt;0&lt;/Ordinal&gt;&lt;GlobalOrder&gt;0&lt;/GlobalOrder&gt;&lt;GalleryItemID&gt;{00000000-0000-0000-0000-000000000000}&lt;/GalleryItemID&gt;&lt;GalleryID&gt;{00000000-0000-0000-0000-000000000000}&lt;/GalleryID&gt;&lt;GalleryObjectID&gt;{00000000-0000-0000-0000-000000000000}&lt;/GalleryObjectID&gt;&lt;OnlyLogical&gt;0&lt;/OnlyLogical&gt;&lt;Caption&gt;FLIGHT&lt;/Caption&gt;&lt;Size&gt;0&lt;/Size&gt;&lt;Description&gt;&lt;/Description&gt;&lt;Nature&gt;&lt;/Nature&gt;&lt;Relations&gt;&lt;Id&gt;{8DAAF463-552E-4894-9ED0-4DC72D684782}&lt;/Id&gt;&lt;Id&gt;{2E8963DB-958B-4CA1-819F-A791E7FF4E0A}&lt;/Id&gt;&lt;Id&gt;{05A12837-4349-49CD-A54E-AD9D1A20CB4F}&lt;/Id&gt;&lt;/Relations&gt;&lt;Attributes/&gt;&lt;UniqueIdentifiers&gt;&lt;LERUniqueIdentifier ObjectType="4011" CSAOName="LERUniqueIdentifier"&gt;&lt;Id&gt;{566AD413-D8BD-4614-8F53-15589B6B9127}&lt;/Id&gt;&lt;Name&gt;Unique_Identifier1&lt;/Name&gt;&lt;Ordinal&gt;0&lt;/Ordinal&gt;&lt;GlobalOrder&gt;0&lt;/GlobalOrder&gt;&lt;GalleryItemID&gt;{00000000-0000-0000-0000-000000000000}&lt;/GalleryItemID&gt;&lt;GalleryID&gt;{00000000-0000-0000-0000-000000000000}&lt;/GalleryID&gt;&lt;GalleryObjectID&gt;{00000000-0000-0000-0000-000000000000}&lt;/GalleryObjectID&gt;&lt;Caption&gt;Unique_Identifier1&lt;/Caption&gt;&lt;UniqueIdentifierItems/&gt;&lt;Relations&gt;&lt;Id&gt;{8DAAF463-552E-4894-9ED0-4DC72D684782}&lt;/Id&gt;&lt;Id&gt;{2E8963DB-958B-4CA1-819F-A791E7FF4E0A}&lt;/Id&gt;&lt;Id&gt;{05A12837-4349-49CD-A54E-AD9D1A20CB4F}&lt;/Id&gt;&lt;/Relations&gt;&lt;/LERUniqueIdentifier&gt;&lt;/UniqueIdentifiers&gt;&lt;PrimaryIdentifier&gt;&lt;Id&gt;{566AD413-D8BD-4614-8F53-15589B6B9127}&lt;/Id&gt;&lt;/PrimaryIdentifier&gt;&lt;ToDoItems/&gt;&lt;Category/&gt;&lt;/LEREntity&gt;&lt;LEREntity ObjectType="4004" CSAOName="LEREntity"&gt;&lt;Id&gt;{A65A5E4D-8AAE-47F6-A985-04CC5A7D9E38}&lt;/Id&gt;&lt;Name&gt;SEGMENT&lt;/Name&gt;&lt;Ordinal&gt;0&lt;/Ordinal&gt;&lt;GlobalOrder&gt;0&lt;/GlobalOrder&gt;&lt;GalleryItemID&gt;{00000000-0000-0000-0000-000000000000}&lt;/GalleryItemID&gt;&lt;GalleryID&gt;{00000000-0000-0000-0000-000000000000}&lt;/GalleryID&gt;&lt;GalleryObjectID&gt;{00000000-0000-0000-0000-000000000000}&lt;/GalleryObjectID&gt;&lt;OnlyLogical&gt;0&lt;/OnlyLogical&gt;&lt;Caption&gt;SEGMENT&lt;/Caption&gt;&lt;Size&gt;0&lt;/Size&gt;&lt;Description&gt;&lt;/Description&gt;&lt;Nature&gt;&lt;/Nature&gt;&lt;Relations&gt;&lt;Id&gt;{8DAAF463-552E-4894-9ED0-4DC72D684782}&lt;/Id&gt;&lt;Id&gt;{EDC7E0DE-DA0F-4360-854B-1422CF6AF10C}&lt;/Id&gt;&lt;Id&gt;{20159913-BD6E-4899-AE26-05EC27540D3B}&lt;/Id&gt;&lt;/Relations&gt;&lt;Attributes/&gt;&lt;UniqueIdentifiers&gt;&lt;LERUniqueIdentifier ObjectType="4011" CSAOName="LERUniqueIdentifier"&gt;&lt;Id&gt;{DF97EB76-663F-44E0-8036-7F7E9CBD9B62}&lt;/Id&gt;&lt;Name&gt;Unique_Identifier2&lt;/Name&gt;&lt;Ordinal&gt;0&lt;/Ordinal&gt;&lt;GlobalOrder&gt;0&lt;/GlobalOrder&gt;&lt;GalleryItemID&gt;{00000000-0000-0000-0000-000000000000}&lt;/GalleryItemID&gt;&lt;GalleryID&gt;{00000000-0000-0000-0000-000000000000}&lt;/GalleryID&gt;&lt;GalleryObjectID&gt;{00000000-0000-0000-0000-000000000000}&lt;/GalleryObjectID&gt;&lt;Caption&gt;Unique_Identifier2&lt;/Caption&gt;&lt;UniqueIdentifierItems/&gt;&lt;Relations&gt;&lt;Id&gt;{8DAAF463-552E-4894-9ED0-4DC72D684782}&lt;/Id&gt;&lt;Id&gt;{EDC7E0DE-DA0F-4360-854B-1422CF6AF10C}&lt;/Id&gt;&lt;Id&gt;{20159913-BD6E-4899-AE26-05EC27540D3B}&lt;/Id&gt;&lt;/Relations&gt;&lt;/LERUniqueIdentifier&gt;&lt;/UniqueIdentifiers&gt;&lt;PrimaryIdentifier&gt;&lt;Id&gt;{DF97EB76-663F-44E0-8036-7F7E9CBD9B62}&lt;/Id&gt;&lt;/PrimaryIdentifier&gt;&lt;ToDoItems/&gt;&lt;Category/&gt;&lt;/LEREntity&gt;&lt;LEREntity ObjectType="4004" CSAOName="LEREntity"&gt;&lt;Id&gt;{A8B650B9-F8E6-49F2-91D3-6ACFEB20D253}&lt;/Id&gt;&lt;Name&gt;AIRPORT&lt;/Name&gt;&lt;Ordinal&gt;0&lt;/Ordinal&gt;&lt;GlobalOrder&gt;0&lt;/GlobalOrder&gt;&lt;GalleryItemID&gt;{00000000-0000-0000-0000-000000000000}&lt;/GalleryItemID&gt;&lt;GalleryID&gt;{00000000-0000-0000-0000-000000000000}&lt;/GalleryID&gt;&lt;GalleryObjectID&gt;{00000000-0000-0000-0000-000000000000}&lt;/GalleryObjectID&gt;&lt;OnlyLogical&gt;0&lt;/OnlyLogical&gt;&lt;Caption&gt;AIRPORT&lt;/Caption&gt;&lt;Size&gt;0&lt;/Size&gt;&lt;Description&gt;&lt;/Description&gt;&lt;Nature&gt;&lt;/Nature&gt;&lt;Relations&gt;&lt;Id&gt;{EDC7E0DE-DA0F-4360-854B-1422CF6AF10C}&lt;/Id&gt;&lt;Id&gt;{20159913-BD6E-4899-AE26-05EC27540D3B}&lt;/Id&gt;&lt;Id&gt;{C134E1E3-1D12-4CA8-8313-03AB7E6D80DB}&lt;/Id&gt;&lt;/Relations&gt;&lt;Attributes/&gt;&lt;UniqueIdentifiers&gt;&lt;LERUniqueIdentifier ObjectType="4011" CSAOName="LERUniqueIdentifier"&gt;&lt;Id&gt;{1838E7F0-2108-4BF4-B034-6EFC428B3DB6}&lt;/Id&gt;&lt;Name&gt;Unique_Identifier4&lt;/Name&gt;&lt;Ordinal&gt;0&lt;/Ordinal&gt;&lt;GlobalOrder&gt;0&lt;/GlobalOrder&gt;&lt;GalleryItemID&gt;{00000000-0000-0000-0000-000000000000}&lt;/GalleryItemID&gt;&lt;GalleryID&gt;{00000000-0000-0000-0000-000000000000}&lt;/GalleryID&gt;&lt;GalleryObjectID&gt;{00000000-0000-0000-0000-000000000000}&lt;/GalleryObjectID&gt;&lt;Caption&gt;Unique_Identifier4&lt;/Caption&gt;&lt;UniqueIdentifierItems/&gt;&lt;Relations&gt;&lt;Id&gt;{EDC7E0DE-DA0F-4360-854B-1422CF6AF10C}&lt;/Id&gt;&lt;Id&gt;{20159913-BD6E-4899-AE26-05EC27540D3B}&lt;/Id&gt;&lt;Id&gt;{C134E1E3-1D12-4CA8-8313-03AB7E6D80DB}&lt;/Id&gt;&lt;/Relations&gt;&lt;/LERUniqueIdentifier&gt;&lt;/UniqueIdentifiers&gt;&lt;PrimaryIdentifier&gt;&lt;Id&gt;{1838E7F0-2108-4BF4-B034-6EFC428B3DB6}&lt;/Id&gt;&lt;/PrimaryIdentifier&gt;&lt;ToDoItems/&gt;&lt;Category/&gt;&lt;/LEREntity&gt;&lt;LEREntity ObjectType="4004" CSAOName="LEREntity"&gt;&lt;Id&gt;{9FEDE1B8-AE03-4034-9750-699CB6B22C8F}&lt;/Id&gt;&lt;Name&gt;AIRLINE HUB&lt;/Name&gt;&lt;Ordinal&gt;0&lt;/Ordinal&gt;&lt;GlobalOrder&gt;0&lt;/GlobalOrder&gt;&lt;GalleryItemID&gt;{00000000-0000-0000-0000-000000000000}&lt;/GalleryItemID&gt;&lt;GalleryID&gt;{00000000-0000-0000-0000-000000000000}&lt;/GalleryID&gt;&lt;GalleryObjectID&gt;{00000000-0000-0000-0000-000000000000}&lt;/GalleryObjectID&gt;&lt;OnlyLogical&gt;0&lt;/OnlyLogical&gt;&lt;Caption&gt;AIRLINE HUB&lt;/Caption&gt;&lt;Size&gt;0&lt;/Size&gt;&lt;Description&gt;&lt;/Description&gt;&lt;Nature&gt;&lt;/Nature&gt;&lt;Relations&gt;&lt;Id&gt;{E1282207-BC87-4E97-A51E-17CBDD5D42CC}&lt;/Id&gt;&lt;Id&gt;{C134E1E3-1D12-4CA8-8313-03AB7E6D80DB}&lt;/Id&gt;&lt;/Relations&gt;&lt;Attributes/&gt;&lt;UniqueIdentifiers&gt;&lt;LERUniqueIdentifier ObjectType="4011" CSAOName="LERUniqueIdentifier"&gt;&lt;Id&gt;{4D30BDFE-1F32-403C-BE8C-B9BF02EB6429}&lt;/Id&gt;&lt;Name&gt;Unique_Identifier5&lt;/Name&gt;&lt;Ordinal&gt;0&lt;/Ordinal&gt;&lt;GlobalOrder&gt;0&lt;/GlobalOrder&gt;&lt;GalleryItemID&gt;{00000000-0000-0000-0000-000000000000}&lt;/GalleryItemID&gt;&lt;GalleryID&gt;{00000000-0000-0000-0000-000000000000}&lt;/GalleryID&gt;&lt;GalleryObjectID&gt;{00000000-0000-0000-0000-000000000000}&lt;/GalleryObjectID&gt;&lt;Caption&gt;Unique_Identifier5&lt;/Caption&gt;&lt;UniqueIdentifierItems/&gt;&lt;Relations&gt;&lt;Id&gt;{E1282207-BC87-4E97-A51E-17CBDD5D42CC}&lt;/Id&gt;&lt;Id&gt;{C134E1E3-1D12-4CA8-8313-03AB7E6D80DB}&lt;/Id&gt;&lt;/Relations&gt;&lt;/LERUniqueIdentifier&gt;&lt;/UniqueIdentifiers&gt;&lt;PrimaryIdentifier&gt;&lt;Id&gt;{4D30BDFE-1F32-403C-BE8C-B9BF02EB6429}&lt;/Id&gt;&lt;/PrimaryIdentifier&gt;&lt;ToDoItems/&gt;&lt;Category/&gt;&lt;/LEREntity&gt;&lt;LEREntity ObjectType="4004" CSAOName="LEREntity"&gt;&lt;Id&gt;{73FF3EAB-FA33-4E71-98EE-7CEAECAF0835}&lt;/Id&gt;&lt;Name&gt;AIRLINE&lt;/Name&gt;&lt;Ordinal&gt;0&lt;/Ordinal&gt;&lt;GlobalOrder&gt;0&lt;/GlobalOrder&gt;&lt;GalleryItemID&gt;{00000000-0000-0000-0000-000000000000}&lt;/GalleryItemID&gt;&lt;GalleryID&gt;{00000000-0000-0000-0000-000000000000}&lt;/GalleryID&gt;&lt;GalleryObjectID&gt;{00000000-0000-0000-0000-000000000000}&lt;/GalleryObjectID&gt;&lt;OnlyLogical&gt;0&lt;/OnlyLogical&gt;&lt;Caption&gt;AIRLINE&lt;/Caption&gt;&lt;Size&gt;0&lt;/Size&gt;&lt;Description&gt;&lt;/Description&gt;&lt;Nature&gt;&lt;/Nature&gt;&lt;Relations&gt;&lt;Id&gt;{2E8963DB-958B-4CA1-819F-A791E7FF4E0A}&lt;/Id&gt;&lt;Id&gt;{E1282207-BC87-4E97-A51E-17CBDD5D42CC}&lt;/Id&gt;&lt;/Relations&gt;&lt;Attributes/&gt;&lt;UniqueIdentifiers&gt;&lt;LERUniqueIdentifier ObjectType="4011" CSAOName="LERUniqueIdentifier"&gt;&lt;Id&gt;{750A6D96-9FFC-4957-BBDC-49275255DDED}&lt;/Id&gt;&lt;Name&gt;Unique_Identifier6&lt;/Name&gt;&lt;Ordinal&gt;0&lt;/Ordinal&gt;&lt;GlobalOrder&gt;0&lt;/GlobalOrder&gt;&lt;GalleryItemID&gt;{00000000-0000-0000-0000-000000000000}&lt;/GalleryItemID&gt;&lt;GalleryID&gt;{00000000-0000-0000-0000-000000000000}&lt;/GalleryID&gt;&lt;GalleryObjectID&gt;{00000000-0000-0000-0000-000000000000}&lt;/GalleryObjectID&gt;&lt;Caption&gt;Unique_Identifier6&lt;/Caption&gt;&lt;UniqueIdentifierItems/&gt;&lt;Relations&gt;&lt;Id&gt;{2E8963DB-958B-4CA1-819F-A791E7FF4E0A}&lt;/Id&gt;&lt;Id&gt;{E1282207-BC87-4E97-A51E-17CBDD5D42CC}&lt;/Id&gt;&lt;/Relations&gt;&lt;/LERUniqueIdentifier&gt;&lt;/UniqueIdentifiers&gt;&lt;PrimaryIdentifier&gt;&lt;Id&gt;{750A6D96-9FFC-4957-BBDC-49275255DDED}&lt;/Id&gt;&lt;/PrimaryIdentifier&gt;&lt;ToDoItems/&gt;&lt;Category/&gt;&lt;/LEREntity&gt;&lt;LEREntity ObjectType="4004" CSAOName="LEREntity"&gt;&lt;Id&gt;{E73C556E-8EAD-45C3-8C6C-455EFE009896}&lt;/Id&gt;&lt;Name&gt;BOOKING&lt;/Name&gt;&lt;Ordinal&gt;0&lt;/Ordinal&gt;&lt;GlobalOrder&gt;0&lt;/GlobalOrder&gt;&lt;GalleryItemID&gt;{00000000-0000-0000-0000-000000000000}&lt;/GalleryItemID&gt;&lt;GalleryID&gt;{00000000-0000-0000-0000-000000000000}&lt;/GalleryID&gt;&lt;GalleryObjectID&gt;{00000000-0000-0000-0000-000000000000}&lt;/GalleryObjectID&gt;&lt;OnlyLogical&gt;0&lt;/OnlyLogical&gt;&lt;Caption&gt;BOOKING&lt;/Caption&gt;&lt;Size&gt;0&lt;/Size&gt;&lt;Description&gt;&lt;/Description&gt;&lt;Nature&gt;&lt;/Nature&gt;&lt;Relations&gt;&lt;Id&gt;{05A12837-4349-49CD-A54E-AD9D1A20CB4F}&lt;/Id&gt;&lt;Id&gt;{086F513C-E661-4292-9E4F-8FA8C4C817BE}&lt;/Id&gt;&lt;/Relations&gt;&lt;Attributes/&gt;&lt;UniqueIdentifiers&gt;&lt;LERUniqueIdentifier ObjectType="4011" CSAOName="LERUniqueIdentifier"&gt;&lt;Id&gt;{A714E842-C2D1-429A-BC76-137005D20A02}&lt;/Id&gt;&lt;Name&gt;Unique_Identifier7&lt;/Name&gt;&lt;Ordinal&gt;0&lt;/Ordinal&gt;&lt;GlobalOrder&gt;0&lt;/GlobalOrder&gt;&lt;GalleryItemID&gt;{00000000-0000-0000-0000-000000000000}&lt;/GalleryItemID&gt;&lt;GalleryID&gt;{00000000-0000-0000-0000-000000000000}&lt;/GalleryID&gt;&lt;GalleryObjectID&gt;{00000000-0000-0000-0000-000000000000}&lt;/GalleryObjectID&gt;&lt;Caption&gt;Unique_Identifier7&lt;/Caption&gt;&lt;UniqueIdentifierItems/&gt;&lt;Relations&gt;&lt;Id&gt;{05A12837-4349-49CD-A54E-AD9D1A20CB4F}&lt;/Id&gt;&lt;Id&gt;{086F513C-E661-4292-9E4F-8FA8C4C817BE}&lt;/Id&gt;&lt;/Relations&gt;&lt;/LERUniqueIdentifier&gt;&lt;/UniqueIdentifiers&gt;&lt;PrimaryIdentifier&gt;&lt;Id&gt;{A714E842-C2D1-429A-BC76-137005D20A02}&lt;/Id&gt;&lt;/PrimaryIdentifier&gt;&lt;ToDoItems/&gt;&lt;Category/&gt;&lt;/LEREntity&gt;&lt;LEREntity ObjectType="4004" CSAOName="LEREntity"&gt;&lt;Id&gt;{B6B937F3-1340-4F80-8B87-B82EAA33FA08}&lt;/Id&gt;&lt;Name&gt;PASSENGER&lt;/Name&gt;&lt;Ordinal&gt;0&lt;/Ordinal&gt;&lt;GlobalOrder&gt;0&lt;/GlobalOrder&gt;&lt;GalleryItemID&gt;{00000000-0000-0000-0000-000000000000}&lt;/GalleryItemID&gt;&lt;GalleryID&gt;{00000000-0000-0000-0000-000000000000}&lt;/GalleryID&gt;&lt;GalleryObjectID&gt;{00000000-0000-0000-0000-000000000000}&lt;/GalleryObjectID&gt;&lt;OnlyLogical&gt;0&lt;/OnlyLogical&gt;&lt;Caption&gt;PASSENGER&lt;/Caption&gt;&lt;Size&gt;0&lt;/Size&gt;&lt;Description&gt;&lt;/Description&gt;&lt;Nature&gt;&lt;/Nature&gt;&lt;Relations&gt;&lt;Id&gt;{086F513C-E661-4292-9E4F-8FA8C4C817BE}&lt;/Id&gt;&lt;/Relations&gt;&lt;Attributes/&gt;&lt;UniqueIdentifiers&gt;&lt;LERUniqueIdentifier ObjectType="4011" CSAOName="LERUniqueIdentifier"&gt;&lt;Id&gt;{E8DDF385-FB80-4A6E-BA04-0C6DD88B5141}&lt;/Id&gt;&lt;Name&gt;Unique_Identifier8&lt;/Name&gt;&lt;Ordinal&gt;0&lt;/Ordinal&gt;&lt;GlobalOrder&gt;0&lt;/GlobalOrder&gt;&lt;GalleryItemID&gt;{00000000-0000-0000-0000-000000000000}&lt;/GalleryItemID&gt;&lt;GalleryID&gt;{00000000-0000-0000-0000-000000000000}&lt;/GalleryID&gt;&lt;GalleryObjectID&gt;{00000000-0000-0000-0000-000000000000}&lt;/GalleryObjectID&gt;&lt;Caption&gt;Unique_Identifier8&lt;/Caption&gt;&lt;UniqueIdentifierItems/&gt;&lt;Relations&gt;&lt;Id&gt;{086F513C-E661-4292-9E4F-8FA8C4C817BE}&lt;/Id&gt;&lt;/Relations&gt;&lt;/LERUniqueIdentifier&gt;&lt;/UniqueIdentifiers&gt;&lt;PrimaryIdentifier&gt;&lt;Id&gt;{E8DDF385-FB80-4A6E-BA04-0C6DD88B5141}&lt;/Id&gt;&lt;/PrimaryIdentifier&gt;&lt;ToDoItems/&gt;&lt;Category/&gt;&lt;/LEREntity&gt;&lt;/Entities&gt;&lt;Relations&gt;&lt;LERRelation ObjectType="4005" CSAOName="LERRelation"&gt;&lt;Id&gt;{8DAAF463-552E-4894-9ED0-4DC72D684782}&lt;/Id&gt;&lt;Name&gt;IS COMPSED OF&lt;/Name&gt;&lt;Ordinal&gt;0&lt;/Ordinal&gt;&lt;GlobalOrder&gt;0&lt;/GlobalOrder&gt;&lt;O1&gt;&lt;Id&gt;{9A2B1CD2-2B6F-466F-82B2-E644B42C0F9D}&lt;/Id&gt;&lt;/O1&gt;&lt;O2&gt;&lt;Id&gt;{A65A5E4D-8AAE-47F6-A985-04CC5A7D9E38}&lt;/Id&gt;&lt;/O2&gt;&lt;Card1Low&gt;1&lt;/Card1Low&gt;&lt;Card1High&gt;1&lt;/Card1High&gt;&lt;Card2Low&gt;0&lt;/Card2Low&gt;&lt;Card2High&gt;-1&lt;/Card2High&gt;&lt;Caption&gt;IS COMPSED OF&lt;/Caption&gt;&lt;OnlyLogical&gt;0&lt;/OnlyLogical&gt;&lt;Dependency1&gt;0&lt;/Dependency1&gt;&lt;Dependency2&gt;0&lt;/Dependency2&gt;&lt;Description&gt;&lt;/Description&gt;&lt;ToDoItems/&gt;&lt;ForeignUniqueIdentifier&gt;&lt;Id&gt;{566AD413-D8BD-4614-8F53-15589B6B9127}&lt;/Id&gt;&lt;/ForeignUniqueIdentifier&gt;&lt;ForeignUniqueIdentifierOpposite&gt;&lt;Id&gt;{DF97EB76-663F-44E0-8036-7F7E9CBD9B62}&lt;/Id&gt;&lt;/ForeignUniqueIdentifierOpposite&gt;&lt;Category/&gt;&lt;/LERRelation&gt;&lt;LERRelation ObjectType="4005" CSAOName="LERRelation"&gt;&lt;Id&gt;{EDC7E0DE-DA0F-4360-854B-1422CF6AF10C}&lt;/Id&gt;&lt;Name&gt;STARTS AT&lt;/Name&gt;&lt;Ordinal&gt;0&lt;/Ordinal&gt;&lt;GlobalOrder&gt;0&lt;/GlobalOrder&gt;&lt;O1&gt;&lt;Id&gt;{A8B650B9-F8E6-49F2-91D3-6ACFEB20D253}&lt;/Id&gt;&lt;/O1&gt;&lt;O2&gt;&lt;Id&gt;{A65A5E4D-8AAE-47F6-A985-04CC5A7D9E38}&lt;/Id&gt;&lt;/O2&gt;&lt;Card1Low&gt;1&lt;/Card1Low&gt;&lt;Card1High&gt;1&lt;/Card1High&gt;&lt;Card2Low&gt;0&lt;/Card2Low&gt;&lt;Card2High&gt;-1&lt;/Card2High&gt;&lt;Caption&gt;STARTS AT&lt;/Caption&gt;&lt;OnlyLogical&gt;0&lt;/OnlyLogical&gt;&lt;Dependency1&gt;0&lt;/Dependency1&gt;&lt;Dependency2&gt;0&lt;/Dependency2&gt;&lt;Description&gt;&lt;/Description&gt;&lt;ToDoItems/&gt;&lt;ForeignUniqueIdentifier&gt;&lt;Id&gt;{1838E7F0-2108-4BF4-B034-6EFC428B3DB6}&lt;/Id&gt;&lt;/ForeignUniqueIdentifier&gt;&lt;ForeignUniqueIdentifierOpposite&gt;&lt;Id&gt;{DF97EB76-663F-44E0-8036-7F7E9CBD9B62}&lt;/Id&gt;&lt;/ForeignUniqueIdentifierOpposite&gt;&lt;Category/&gt;&lt;/LERRelation&gt;&lt;LERRelation ObjectType="4005" CSAOName="LERRelation"&gt;&lt;Id&gt;{20159913-BD6E-4899-AE26-05EC27540D3B}&lt;/Id&gt;&lt;Name&gt;ENDS AT&lt;/Name&gt;&lt;Ordinal&gt;0&lt;/Ordinal&gt;&lt;GlobalOrder&gt;0&lt;/GlobalOrder&gt;&lt;O1&gt;&lt;Id&gt;{A8B650B9-F8E6-49F2-91D3-6ACFEB20D253}&lt;/Id&gt;&lt;/O1&gt;&lt;O2&gt;&lt;Id&gt;{A65A5E4D-8AAE-47F6-A985-04CC5A7D9E38}&lt;/Id&gt;&lt;/O2&gt;&lt;Card1Low&gt;1&lt;/Card1Low&gt;&lt;Card1High&gt;1&lt;/Card1High&gt;&lt;Card2Low&gt;0&lt;/Card2Low&gt;&lt;Card2High&gt;-1&lt;/Card2High&gt;&lt;Caption&gt;ENDS AT&lt;/Caption&gt;&lt;OnlyLogical&gt;0&lt;/OnlyLogical&gt;&lt;Dependency1&gt;0&lt;/Dependency1&gt;&lt;Dependency2&gt;0&lt;/Dependency2&gt;&lt;Description&gt;&lt;/Description&gt;&lt;ToDoItems/&gt;&lt;ForeignUniqueIdentifier&gt;&lt;Id&gt;{1838E7F0-2108-4BF4-B034-6EFC428B3DB6}&lt;/Id&gt;&lt;/ForeignUniqueIdentifier&gt;&lt;ForeignUniqueIdentifierOpposite&gt;&lt;Id&gt;{DF97EB76-663F-44E0-8036-7F7E9CBD9B62}&lt;/Id&gt;&lt;/ForeignUniqueIdentifierOpposite&gt;&lt;Category/&gt;&lt;/LERRelation&gt;&lt;LERRelation ObjectType="4005" CSAOName="LERRelation"&gt;&lt;Id&gt;{2E8963DB-958B-4CA1-819F-A791E7FF4E0A}&lt;/Id&gt;&lt;Name&gt;OFFERS&lt;/Name&gt;&lt;Ordinal&gt;0&lt;/Ordinal&gt;&lt;GlobalOrder&gt;0&lt;/GlobalOrder&gt;&lt;O1&gt;&lt;Id&gt;{73FF3EAB-FA33-4E71-98EE-7CEAECAF0835}&lt;/Id&gt;&lt;/O1&gt;&lt;O2&gt;&lt;Id&gt;{9A2B1CD2-2B6F-466F-82B2-E644B42C0F9D}&lt;/Id&gt;&lt;/O2&gt;&lt;Card1Low&gt;1&lt;/Card1Low&gt;&lt;Card1High&gt;1&lt;/Card1High&gt;&lt;Card2Low&gt;0&lt;/Card2Low&gt;&lt;Card2High&gt;-1&lt;/Card2High&gt;&lt;Caption&gt;OFFERS&lt;/Caption&gt;&lt;OnlyLogical&gt;0&lt;/OnlyLogical&gt;&lt;Dependency1&gt;0&lt;/Dependency1&gt;&lt;Dependency2&gt;0&lt;/Dependency2&gt;&lt;Description&gt;&lt;/Description&gt;&lt;ToDoItems/&gt;&lt;ForeignUniqueIdentifier&gt;&lt;Id&gt;{750A6D96-9FFC-4957-BBDC-49275255DDED}&lt;/Id&gt;&lt;/ForeignUniqueIdentifier&gt;&lt;ForeignUniqueIdentifierOpposite&gt;&lt;Id&gt;{566AD413-D8BD-4614-8F53-15589B6B9127}&lt;/Id&gt;&lt;/ForeignUniqueIdentifierOpposite&gt;&lt;Category/&gt;&lt;/LERRelation&gt;&lt;LERRelation ObjectType="4005" CSAOName="LERRelation"&gt;&lt;Id&gt;{E1282207-BC87-4E97-A51E-17CBDD5D42CC}&lt;/Id&gt;&lt;Name&gt;AIRLINE - AIRLINE HUB&lt;/Name&gt;&lt;Ordinal&gt;0&lt;/Ordinal&gt;&lt;GlobalOrder&gt;0&lt;/GlobalOrder&gt;&lt;O1&gt;&lt;Id&gt;{73FF3EAB-FA33-4E71-98EE-7CEAECAF0835}&lt;/Id&gt;&lt;/O1&gt;&lt;O2&gt;&lt;Id&gt;{9FEDE1B8-AE03-4034-9750-699CB6B22C8F}&lt;/Id&gt;&lt;/O2&gt;&lt;Card1Low&gt;1&lt;/Card1Low&gt;&lt;Card1High&gt;1&lt;/Card1High&gt;&lt;Card2Low&gt;1&lt;/Card2Low&gt;&lt;Card2High&gt;-1&lt;/Card2High&gt;&lt;Caption&gt;AIRLINE - AIRLINE HUB&lt;/Caption&gt;&lt;OnlyLogical&gt;0&lt;/OnlyLogical&gt;&lt;Dependency1&gt;0&lt;/Dependency1&gt;&lt;Dependency2&gt;1&lt;/Dependency2&gt;&lt;Description&gt;&lt;/Description&gt;&lt;ToDoItems/&gt;&lt;ForeignUniqueIdentifier&gt;&lt;Id&gt;{750A6D96-9FFC-4957-BBDC-49275255DDED}&lt;/Id&gt;&lt;/ForeignUniqueIdentifier&gt;&lt;ForeignUniqueIdentifierOpposite&gt;&lt;Id&gt;{4D30BDFE-1F32-403C-BE8C-B9BF02EB6429}&lt;/Id&gt;&lt;/ForeignUniqueIdentifierOpposite&gt;&lt;Category/&gt;&lt;/LERRelation&gt;&lt;LERRelation ObjectType="4005" CSAOName="LERRelation"&gt;&lt;Id&gt;{C134E1E3-1D12-4CA8-8313-03AB7E6D80DB}&lt;/Id&gt;&lt;Name&gt;AIRPORT - AIRLINE HUB&lt;/Name&gt;&lt;Ordinal&gt;0&lt;/Ordinal&gt;&lt;GlobalOrder&gt;0&lt;/GlobalOrder&gt;&lt;O1&gt;&lt;Id&gt;{A8B650B9-F8E6-49F2-91D3-6ACFEB20D253}&lt;/Id&gt;&lt;/O1&gt;&lt;O2&gt;&lt;Id&gt;{9FEDE1B8-AE03-4034-9750-699CB6B22C8F}&lt;/Id&gt;&lt;/O2&gt;&lt;Card1Low&gt;1&lt;/Card1Low&gt;&lt;Card1High&gt;1&lt;/Card1High&gt;&lt;Card2Low&gt;1&lt;/Card2Low&gt;&lt;Card2High&gt;-1&lt;/Card2High&gt;&lt;Caption&gt;AIRPORT - AIRLINE HUB&lt;/Caption&gt;&lt;OnlyLogical&gt;0&lt;/OnlyLogical&gt;&lt;Dependency1&gt;0&lt;/Dependency1&gt;&lt;Dependency2&gt;1&lt;/Dependency2&gt;&lt;Description&gt;&lt;/Description&gt;&lt;ToDoItems/&gt;&lt;ForeignUniqueIdentifier&gt;&lt;Id&gt;{1838E7F0-2108-4BF4-B034-6EFC428B3DB6}&lt;/Id&gt;&lt;/ForeignUniqueIdentifier&gt;&lt;ForeignUniqueIdentifierOpposite&gt;&lt;Id&gt;{4D30BDFE-1F32-403C-BE8C-B9BF02EB6429}&lt;/Id&gt;&lt;/ForeignUniqueIdentifierOpposite&gt;&lt;Category/&gt;&lt;/LERRelation&gt;&lt;LERRelation ObjectType="4005" CSAOName="LERRelation"&gt;&lt;Id&gt;{05A12837-4349-49CD-A54E-AD9D1A20CB4F}&lt;/Id&gt;&lt;Name&gt;FLIGHT - BOOKING&lt;/Name&gt;&lt;Ordinal&gt;0&lt;/Ordinal&gt;&lt;GlobalOrder&gt;0&lt;/GlobalOrder&gt;&lt;O1&gt;&lt;Id&gt;{9A2B1CD2-2B6F-466F-82B2-E644B42C0F9D}&lt;/Id&gt;&lt;/O1&gt;&lt;O2&gt;&lt;Id&gt;{E73C556E-8EAD-45C3-8C6C-455EFE009896}&lt;/Id&gt;&lt;/O2&gt;&lt;Card1Low&gt;1&lt;/Card1Low&gt;&lt;Card1High&gt;1&lt;/Card1High&gt;&lt;Card2Low&gt;1&lt;/Card2Low&gt;&lt;Card2High&gt;-1&lt;/Card2High&gt;&lt;Caption&gt;FLIGHT - BOOKING&lt;/Caption&gt;&lt;OnlyLogical&gt;0&lt;/OnlyLogical&gt;&lt;Dependency1&gt;0&lt;/Dependency1&gt;&lt;Dependency2&gt;1&lt;/Dependency2&gt;&lt;Description&gt;&lt;/Description&gt;&lt;ToDoItems/&gt;&lt;ForeignUniqueIdentifier&gt;&lt;Id&gt;{566AD413-D8BD-4614-8F53-15589B6B9127}&lt;/Id&gt;&lt;/ForeignUniqueIdentifier&gt;&lt;ForeignUniqueIdentifierOpposite&gt;&lt;Id&gt;{A714E842-C2D1-429A-BC76-137005D20A02}&lt;/Id&gt;&lt;/ForeignUniqueIdentifierOpposite&gt;&lt;Category/&gt;&lt;/LERRelation&gt;&lt;LERRelation ObjectType="4005" CSAOName="LERRelation"&gt;&lt;Id&gt;{086F513C-E661-4292-9E4F-8FA8C4C817BE}&lt;/Id&gt;&lt;Name&gt;PASSENGER - BOOKING&lt;/Name&gt;&lt;Ordinal&gt;0&lt;/Ordinal&gt;&lt;GlobalOrder&gt;0&lt;/GlobalOrder&gt;&lt;O1&gt;&lt;Id&gt;{B6B937F3-1340-4F80-8B87-B82EAA33FA08}&lt;/Id&gt;&lt;/O1&gt;&lt;O2&gt;&lt;Id&gt;{E73C556E-8EAD-45C3-8C6C-455EFE009896}&lt;/Id&gt;&lt;/O2&gt;&lt;Card1Low&gt;1&lt;/Card1Low&gt;&lt;Card1High&gt;1&lt;/Card1High&gt;&lt;Card2Low&gt;1&lt;/Card2Low&gt;&lt;Card2High&gt;-1&lt;/Card2High&gt;&lt;Caption&gt;PASSENGER - BOOKING&lt;/Caption&gt;&lt;OnlyLogical&gt;0&lt;/OnlyLogical&gt;&lt;Dependency1&gt;0&lt;/Dependency1&gt;&lt;Dependency2&gt;1&lt;/Dependency2&gt;&lt;Description&gt;&lt;/Description&gt;&lt;ToDoItems/&gt;&lt;ForeignUniqueIdentifier&gt;&lt;Id&gt;{E8DDF385-FB80-4A6E-BA04-0C6DD88B5141}&lt;/Id&gt;&lt;/ForeignUniqueIdentifier&gt;&lt;ForeignUniqueIdentifierOpposite&gt;&lt;Id&gt;{A714E842-C2D1-429A-BC76-137005D20A02}&lt;/Id&gt;&lt;/ForeignUniqueIdentifierOpposite&gt;&lt;Category/&gt;&lt;/LERRelation&gt;&lt;/Relations&gt;&lt;Domains/&gt;&lt;Rules/&gt;&lt;Defaults/&gt;&lt;Inheritances/&gt;&lt;InheritancesChild/&gt;&lt;InheritancesParent/&gt;&lt;/LERModel&gt;
</SerializedModel><ImportedIds>{4DA3B5EB-37F2-4810-A5EC-A0086A4CB268}
{C3D0F419-EBCC-4D06-9458-C06B572601FC}
{46889D0E-88F1-49FA-882F-92DD10A676DB}
{5778A5D4-3559-4079-BD4A-E131F7979A5E}
{B859F61F-6358-4BF3-AF2D-DA32F06D3D95}
{458C3183-90BE-492A-9ABB-5FCEFB8E0BD7}
{8624E532-F1B5-4B96-8315-663734E91847}
{6AFEF0BA-21FF-4349-B973-89AFF35E35B0}
{00000000-0000-0000-0000-000000000000}
{0023E762-2017-4B5B-955E-F3EE0E1CEF13}
{00000000-0000-0000-0000-000000000000}
{00000000-0000-0000-0000-000000000000}
{00000000-0000-0000-0000-000000000000}
{00000000-0000-0000-0000-000000000000}
{00000000-0000-0000-0000-000000000000}
{00000000-0000-0000-0000-000000000000}
{4F3E62FB-7507-4B5E-972F-27E756350073}
{C6606D33-8FF0-417C-91C3-21BA587867D4}
{3F5DD6FC-A9AA-4C39-985A-EAEAB3E7ECDB}
{00000000-0000-0000-0000-000000000000}
{5037E2CC-1760-41FC-AD29-F7F5C5A7D4AF}
{533FC8B9-C6EB-4643-80F2-F455C6A04B6C}
{1A704A3E-BF01-4C46-B180-56F160BE26FD}
{4D30BDFE-1F32-403C-BE8C-B9BF02EB6429}
{E8DDF385-FB80-4A6E-BA04-0C6DD88B5141}
{A714E842-C2D1-429A-BC76-137005D20A02}
{750A6D96-9FFC-4957-BBDC-49275255DDED}
{1838E7F0-2108-4BF4-B034-6EFC428B3DB6}
{DF97EB76-663F-44E0-8036-7F7E9CBD9B62}
{566AD413-D8BD-4614-8F53-15589B6B9127}
{9FEDE1B8-AE03-4034-9750-699CB6B22C8F}
{E1282207-BC87-4E97-A51E-17CBDD5D42CC}
{C134E1E3-1D12-4CA8-8313-03AB7E6D80DB}
{EDC7E0DE-DA0F-4360-854B-1422CF6AF10C}
{20159913-BD6E-4899-AE26-05EC27540D3B}
{2E8963DB-958B-4CA1-819F-A791E7FF4E0A}
{05A12837-4349-49CD-A54E-AD9D1A20CB4F}
{8DAAF463-552E-4894-9ED0-4DC72D684782}
{086F513C-E661-4292-9E4F-8FA8C4C817BE}
{B6B937F3-1340-4F80-8B87-B82EAA33FA08}
{E73C556E-8EAD-45C3-8C6C-455EFE009896}
{73FF3EAB-FA33-4E71-98EE-7CEAECAF0835}
{A8B650B9-F8E6-49F2-91D3-6ACFEB20D253}
{A65A5E4D-8AAE-47F6-A985-04CC5A7D9E38}
{9A2B1CD2-2B6F-466F-82B2-E644B42C0F9D}
</ImportedIds><DragIDs>{4DA3B5EB-37F2-4810-A5EC-A0086A4CB268}
{C3D0F419-EBCC-4D06-9458-C06B572601FC}
{46889D0E-88F1-49FA-882F-92DD10A676DB}
{5778A5D4-3559-4079-BD4A-E131F7979A5E}
{B859F61F-6358-4BF3-AF2D-DA32F06D3D95}
{458C3183-90BE-492A-9ABB-5FCEFB8E0BD7}
{8624E532-F1B5-4B96-8315-663734E91847}
{6AFEF0BA-21FF-4349-B973-89AFF35E35B0}
{00000000-0000-0000-0000-000000000000}
{0023E762-2017-4B5B-955E-F3EE0E1CEF13}
{00000000-0000-0000-0000-000000000000}
{00000000-0000-0000-0000-000000000000}
{00000000-0000-0000-0000-000000000000}
{00000000-0000-0000-0000-000000000000}
{00000000-0000-0000-0000-000000000000}
{00000000-0000-0000-0000-000000000000}
{4F3E62FB-7507-4B5E-972F-27E756350073}
{C6606D33-8FF0-417C-91C3-21BA587867D4}
{3F5DD6FC-A9AA-4C39-985A-EAEAB3E7ECDB}
{00000000-0000-0000-0000-000000000000}
{5037E2CC-1760-41FC-AD29-F7F5C5A7D4AF}
{533FC8B9-C6EB-4643-80F2-F455C6A04B6C}
{1A704A3E-BF01-4C46-B180-56F160BE26FD}
</DragIDs><ImportedIdsNoOwned></ImportedIdsNoOwned></GalleryItem>
